Metadata-Version: 2.1
Name: dffml-config-yaml
Version: 0.1.0.post0
Summary: DFFML config dffml-config-yaml
Home-page: https://github.com/intel/dffml/blob/master/configloader/yaml/README.md
Author: John Andersen
Author-email: john.s.andersen@intel.com
Maintainer: John Andersen
Maintainer-email: john.s.andersen@intel.com
License: MIT
Keywords: dffml
Platform: UNKNOWN
Classifier: Development Status :: 3 - Alpha
Classifier: Intended Audience :: Developers
Classifier: License :: OSI Approved :: MIT License
Classifier: Natural Language :: English
Classifier: Operating System :: OS Independent
Classifier: Programming Language :: Python :: 3 :: Only
Classifier: Programming Language :: Python :: 3.7
Classifier: Programming Language :: Python :: Implementation :: CPython
Classifier: Programming Language :: Python :: Implementation :: PyPy
License-File: LICENSE
Requires-Dist: dffml (>=0.4.0)
Requires-Dist: PyYAML (>=5.1.2)
